webquest_mcp/__init__.py
webquest_mcp/app.py
webquest_mcp/app_state.py
webquest_mcp/main.py
webquest_mcp/py.typed
webquest_mcp/token_generator.py
webquest_mcp-0.15.3.dist-info/WHEEL
webquest_mcp-0.15.3.dist-info/entry_points.txt
webquest_mcp-0.15.3.dist-info/METADATA
webquest_mcp-0.15.3.dist-info/RECORD
