Metadata-Version: 2.4
Name: webquest-mcp
Version: 0.15.3
Summary: WebQuest MCP is a Model Context Protocol (MCP) server that exposes powerful web search and scraping tools to AI agents and MCP-compatible clients.
License-Expression: Apache-2.0
Requires-Dist: fastmcp>=2.13.1
Requires-Dist: pydantic>=2.12.4
Requires-Dist: pydantic-settings>=2.12.0
Requires-Dist: pyjwt>=2.10.1
Requires-Dist: webquest>=0.12.7
Requires-Python: >=3.12
Project-URL: Source, https://github.com/mustafametesengul/webquest-mcp
